Workbook

Sheet supply_chain_data
A1: Product type | B1: SKU | C1: Price | D1: Availability | E1: Number of products sold | F1: Revenue generated | G1: Customer demographics | H1: Stock levels | I1: Lead times | J1: Order quantities | K1: Shipping times | L1: Shipping carriers | M1: Shipping costs | N1: Supplier name | O1: Location | P1: Lead time | Q1: Production volumes | R1: Manufacturing lead time | S1: Manufacturing costs | T1: Inspection results | U1: Defect rates | V1: Transportation modes | W1: Routes | X1: Costs | Y1: Profit | Z1: Profit Margin | AA1: Sales To Stock Ratio | AB1: Pass
A2: haircare | B2: SKU0 | C2: 69.808006 | D2: 55 | E2: 802 | F2: 8661.9968 | G2: Non-binary | H2: 58 | I2: 7 | J2: 96 | K2: 4 | L2: Carrier B | M2: 2.9565721 | N2: Supplier 3 | O2: Mumbai | P2: 29 | Q2: 215 | R2: 29 | S2: 46.279879 | T2: Pending | U2: 0.22641036 | V2: Road | W2: Route B | X2: 187.75208 | Y2: =F2-M2-X2-S2 -> 8425.0083 | Z2: =Y2/F2 -> 0.97264043 | AA2: =IFERROR(E2/H2,0) -> 13.827586 | AB2: =IF(T2="Pass",1,0) -> 0
A3: skincare | B3: SKU1 | C3: 14.843523 | D3: 95 | E3: 736 | F3: 7460.9001 | G3: Female | H3: 53 | I3: 30 | J3: 37 | K3: 2 | L3: Carrier A | M3: 9.7165748 | N3: Supplier 3 | O3: Mumbai | P3: 23 | Q3: 517 | R3: 30 | S3: 33.616769 | T3: Pending | U3: 4.854068 | V3: Road | W3: Route B | X3: 503.06558 | Y3: =F3-M3-X3-S3 -> 6914.5011 | Z3: =Y3/F3 -> 0.92676501 | AA3: =IFERROR(E3/H3,0) -> 13.886792 | AB3: =IF(T3="Pass",1,0) -> 0
A4: haircare | B4: SKU2 | C4: 11.319683 | D4: 34 | E4: 8 | F4: 9577.7496 | G4: Unknown | H4: 1 | I4: 10 | J4: 88 | K4: 2 | L4: Carrier B | M4: 8.0544793 | N4: Supplier 1 | O4: Mumbai | P4: 12 | Q4: 971 | R4: 27 | S4: 30.688019 | T4: Pending | U4: 4.5805926 | V4: Air | W4: Route C | X4: 141.92028 | Y4: =F4-M4-X4-S4 -> 9397.0868 | Z4: =Y4/F4 -> 0.98113724 | AA4: =IFERROR(E4/H4,0) -> 8 | AB4: =IF(T4="Pass",1,0) -> 0
A5: skincare | B5: SKU3 | C5: 61.163343 | D5: 68 | E5: 83 | F5: 7766.8364 | G5: Non-binary | H5: 23 | I5: 13 | J5: 59 | K5: 6 | L5: Carrier C | M5: 1.7295686 | N5: Supplier 5 | O5: Kolkata | P5: 24 | Q5: 937 | R5: 18 | S5: 35.624741 | T5: Fail | U5: 4.7466486 | V5: Rail | W5: Route A | X5: 254.77616 | Y5: =F5-M5-X5-S5 -> 7474.706 | Z5: =Y5/F5 -> 0.96238746 | AA5: =IFERROR(E5/H5,0) -> 3.6086957 | AB5: =IF(T5="Pass",1,0) -> 0
A6: skincare | B6: SKU4 | C6: 4.805496 | D6: 26 | E6: 871 | F6: 2686.5052 | G6: Non-binary | H6: 5 | I6: 3 | J6: 56 | K6: 8 | L6: Carrier A | M6: 3.8905479 | N6: Supplier 1 | O6: Delhi | P6: 5 | Q6: 414 | R6: 3 | S6: 92.065161 | T6: Fail | U6: 3.1455795 | V6: Air | W6: Route A | X6: 923.44063 | Y6: =F6-M6-X6-S6 -> 1667.1088 | Z6: =Y6/F6 -> 0.62054927 | AA6: =IFERROR(E6/H6,0) -> 174.2 | AB6: =IF(T6="Pass",1,0) -> 0
A7: haircare | B7: SKU5 | C7: 1.699976 | D7: 87 | E7: 147 | F7: 2828.3487 | G7: Non-binary | H7: 90 | I7: 27 | J7: 66 | K7: 3 | L7: Carrier B | M7: 4.4440989 | N7: Supplier 4 | O7: Bangalore | P7: 10 | Q7: 104 | R7: 17 | S7: 56.766476 | T7: Fail | U7: 2.7791935 | V7: Road | W7: Route A | X7: 235.46124 | Y7: =F7-M7-X7-S7 -> 2531.6769 | Z7: =Y7/F7 -> 0.89510777 | AA7: =IFERROR(E7/H7,0) -> 1.6333333 | AB7: =IF(T7="Pass",1,0) -> 0
A8: skincare | B8: SKU6 | C8: 4.0783329 | D8: 48 | E8: 65 | F8: 7823.4766 | G8: Male | H8: 11 | I8: 15 | J8: 58 | K8: 8 | L8: Carrier C | M8: 3.8807633 | N8: Supplier 3 | O8: Kolkata | P8: 14 | Q8: 314 | R8: 24 | S8: 1.0850686 | T8: Pending | U8: 1.0009106 | V8: Sea | W8: Route A | X8: 134.3691 | Y8: =F8-M8-X8-S8 -> 7684.1416 | Z8: =Y8/F8 -> 0.98219015 | AA8: =IFERROR(E8/H8,0) -> 5.9090909 | AB8: =IF(T8="Pass",1,0) -> 0
A9: cosmetics | B9: SKU7 | C9: 42.958384 | D9: 59 | E9: 426 | F9: 8496.1038 | G9: Female | H9: 93 | I9: 17 | J9: 11 | K9: 1 | L9: Carrier B | M9: 2.3483388 | N9: Supplier 4 | O9: Bangalore | P9: 22 | Q9: 564 | R9: 1 | S9: 99.466109 | T9: Fail | U9: 0.39817719 | V9: Road | W9: Route C | X9: 802.05631 | Y9: =F9-M9-X9-S9 -> 7592.2331 | Z9: =Y9/F9 -> 0.8936135 | AA9: =IFERROR(E9/H9,0) -> 4.5806452 | AB9: =IF(T9="Pass",1,0) -> 0
A10: cosmetics | B10: SKU8 | C10: 68.717597 | D10: 78 | E10: 150 | F10: 7517.3632 | G10: Female | H10: 5 | I10: 10 | J10: 15 | K10: 7 | L10: Carrier C | M10: 3.4047339 | N10: Supplier 4 | O10: Mumbai | P10: 13 | Q10: 769 | R10: 8 | S10: 11.423027 | T10: Pending | U10: 2.7098627 | V10: Sea | W10: Route B | X10: 505.55713 | Y10: =F10-M10-X10-S10 -> 6996.9783 | Z10: =Y10/F10 -> 0.93077561 | AA10: =IFERROR(E10/H10,0) -> 30 | AB10: =IF(T10="Pass",1,0) -> 0
A11: skincare | B11: SKU9 | C11: 64.015733 | D11: 35 | E11: 980 | F11: 4971.146 | G11: Unknown | H11: 14 | I11: 27 | J11: 83 | K11: 1 | L11: Carrier A | M11: 7.1666453 | N11: Supplier 2 | O11: Chennai | P11: 29 | Q11: 963 | R11: 23 | S11: 47.957602 | T11: Pending | U11: 3.8446145 | V11: Rail | W11: Route B | X11: 995.92946 | Y11: =F11-M11-X11-S11 -> 3920.0923 | Z11: =Y11/F11 -> 0.78856913 | AA11: =IFERROR(E11/H11,0) -> 70 | AB11: =IF(T11="Pass",1,0) -> 0
A12: skincare | B12: SKU10 | C12: 15.707796 | D12: 11 | E12: 996 | F12: 2330.9658 | G12: Non-binary | H12: 51 | I12: 13 | J12: 80 | K12: 2 | L12: Carrier C | M12: 8.6732112 | N12: Supplier 5 | O12: Kolkata | P12: 18 | Q12: 830 | R12: 5 | S12: 96.527353 | T12: Pass | U12: 1.7273139 | V12: Road | W12: Route B | X12: 806.10318 | Y12: =F12-M12-X12-S12 -> 1419.6621 | Z12: =Y12/F12 -> 0.60904457 | AA12: =IFERROR(E12/H12,0) -> 19.529412 | AB12: =IF(T12="Pass",1,0) -> 1
A13: skincare | B13: SKU11 | C13: 90.63546 | D13: 95 | E13: 960 | F13: 6099.9441 | G13: Female | H13: 46 | I13: 23 | J13: 60 | K13: 1 | L13: Carrier A | M13: 4.5239431 | N13: Supplier 2 | O13: Kolkata | P13: 28 | Q13: 362 | R13: 11 | S13: 27.592363 | T13: Pending | U13: 0.021169821 | V13: Air | W13: Route A | X13: 126.72303 | Y13: =F13-M13-X13-S13 -> 5941.1048 | Z13: =Y13/F13 -> 0.97396053 | AA13: =IFERROR(E13/H13,0) -> 20.869565 | AB13: =IF(T13="Pass",1,0) -> 0
... A101: haircare | B101: SKU99 | C101: 68.517833 | D101: 17 | E101: 627 | F101: 9185.1858 | G101: Unknown | H101: 55 | I101: 8 | J101: 59 | K101: 6 | L101: Carrier B | M101: 1.3110238 | N101: Supplier 2 | O101: Chennai | P101: 29 | Q101: 921 | R101: 2 | S101: 38.072899 | T101: Fail | U101: 0.34602729 | V101: Rail | W101: Route B | X101: 210.74301 | Y101: =F101-M101-X101-S101 -> 8935.0589 | Z101: =Y101/F101 -> 0.97276844 | AA101: =IFERROR(E101/H101,0) -> 11.4 | AB101: =IF(T101="Pass",1,0) -> 0
Z107: =DIVIDE(100*Y107,F107) -> #NAME? | AA107: =IFERROR(DIVIDE(E107,H107),0) -> 0
Z108: =DIVIDE(100*Y108,F108) -> #NAME? | AA108: =DIVIDE(E108,H108) -> #NAME?
Z109: =DIVIDE(100*Y109,F109) -> #NAME? | AA109: =DIVIDE(E109,H109) -> #NAME?
Z110: =DIVIDE(100*Y110,F110) -> #NAME? | AA110: =DIVIDE(E110,H110) -> #NAME?
Z111: =DIVIDE(100*Y111,F111) -> #NAME? | AA111: =DIVIDE(E111,H111) -> #NAME?
Z112: =DIVIDE(100*Y112,F112) -> #NAME? | AA112: =DIVIDE(E112,H112) -> #NAME?
Z113: =DIVIDE(100*Y113,F113) -> #NAME? | AA113: =DIVIDE(E113,H113) -> #NAME?
Z114: =DIVIDE(100*Y114,F114) -> #NAME? | AA114: =DIVIDE(E114,H114) -> #NAME?
Z115: =DIVIDE(100*Y115,F115) -> #NAME? | AA115: =DIVIDE(E115,H115) -> #NAME?
Z116: =DIVIDE(100*Y116,F116) -> #NAME? | AA116: =DIVIDE(E116,H116) -> #NAME?
Z117: =DIVIDE(100*Y117,F117) -> #NAME? | AA117: =DIVIDE(E117,H117) -> #NAME?
Z118: =DIVIDE(100*Y118,F118) -> #NAME? | AA118: =DIVIDE(E118,H118) -> #NAME?
Z119: =DIVIDE(100*Y119,F119) -> #NAME? | AA119: =DIVIDE(E119,H119) -> #NAME?
... Z132: =DIVIDE(100*Y132,F132) -> #NAME? | AA132: =DIVIDE(E132,H132) -> #NAME?

Sheet PVT Revenue
A1: Total Revenue | B1: =SUM(supply_chain_data!F:F) -> 577604.82
A2: Estimated Profit | B2: =SUM(supply_chain_data!Y:Y) -> 519398.76
A3: Profit Margin | B3: =100*(B2/B1) -> 89.922857
A4: Avg Defect Rate | B4: =AVERAGE(supply_chain_data!U:U) -> 2.277158
A5: Avg Lead Time | B5: =AVERAGE(supply_chain_data!P:P) -> 17.08
A8: Row Labels | B8: Sum of Revenue generated | D8: Row Labels | E8: Sum of Revenue generated
A9: Supplier 1 | B9: 157529 | D9: cosmetics | E9: 161521.27
A10: Supplier 2 | B10: 125467.42 | D10: haircare | E10: 174455.39
A11: Supplier 3 | B11: 97795.98 | D11: skincare | E11: 241628.16
A12: Supplier 4 | B12: 86468.962 | D12: Grand Total | E12: 577604.82
A13: Supplier 5 | B13: 110343.46
A14: Grand Total | B14: 577604.82
D16: Row Labels | E16: Sum of Profit
D17: cosmetics | E17: 0.28278453
D18: haircare | E18: 0.29895738
D19: skincare | E19: 0.41825809
D20: Grand Total | E20: 1
D23: Row Labels | E23: Sum of Profit
D24: Supplier 1 | E24: 0.27076947
D25: Supplier 2 | E25: 0.21774188
D26: Supplier 3 | E26: 0.17334973
D27: Supplier 4 | E27: 0.14602254
D28: Supplier 5 | E28: 0.19211638
D29: Grand Total | E29: 1

Sheet Dashboard Revenue

Sheet PVT Inventory
A1: Row Labels | B1: Sum of Number of products sold | D1: Row Labels | E1: Sum of Number of products sold
A2: cosmetics | B2: 11757 | D2: Supplier 1 | E2: 11080
A3: haircare | B3: 13611 | D3: Supplier 2 | E3: 11068
A4: skincare | B4: 20731 | D4: Supplier 3 | E4: 8083
A5: Grand Total | B5: 46099 | D5: Supplier 4 | E5: 7206
D6: Supplier 5 | E6: 8662
D7: Grand Total | E7: 46099
E13: Row Labels | F13: Average of Number of products sold | G13: Average of Sales To Stock Ratio
A14: Row Labels | B14: Average of Number of products sold | C14: Average of Sales To Stock Ratio | E14: Supplier 1 | F14: 410.37037 | G14: 51.544211
A15: cosmetics | B15: 452.19231 | C15: 16.593001 | E15: Supplier 2 | F15: 503.09091 | G15: 21.693347
A16: haircare | B16: 400.32353 | C16: 17.982247 | E16: Supplier 3 | F16: 538.86667 | G16: 18.851109
A17: skincare | B17: 518.275 | C17: 45.416858 | E17: Supplier 4 | F17: 400.33333 | G17: 10.639173
A18: Grand Total | B18: 460.99 | C18: 28.594887 | E18: Supplier 5 | F18: 481.22222 | G18: 28.681649
E19: Grand Total | F19: 460.99 | G19: 28.594887
B23: =AVERAGE(supply_chain_data!H:H) -> 47.77
B24: =AVERAGE(supply_chain_data!E:E) -> 460.99
B25: =AVERAGE(supply_chain_data!D:D) -> 48.4
B26: =SUM(supply_chain_data!J:J)/COUNT(supply_chain_data!J:J) -> 49.22

Sheet Dashboard Inventory

Sheet PVT Tranportation
A1: Row Labels | B1: Sum of Revenue generated | D1: Row Labels | E1: Average of Shipping times | G1: Row Labels | H1: Average of Defect rates
A2: Air | B2: 0.26962266 | D2: Air | E2: 5.1153846 | G2: Air | H2: 1.8239235
A3: Rail | B3: 0.28564585 | D3: Rail | E3: 6.5714286 | G3: Rail | H3: 2.3188139
A4: Road | B4: 0.27582047 | D4: Road | E4: 4.7241379 | G4: Road | H4: 2.6209385
A5: Sea | B5: 0.16891102 | D5: Sea | E5: 7.1176471 | G5: Sea | H5: 2.3152813
A6: Grand Total | B6: 1 | D6: Grand Total | E6: 5.75 | G6: Grand Total | H6: 2.277158
A11: Row Labels | B11: Average of Defect rates | D11: Row Labels | E11: Average of Pass | G11: Row Labels | H11: Average of Shipping costs
A12: Air | B12: 1.8239235 | D12: Air | E12: 0.19230769 | G12: Air | H12: 6.0178394
A13: Rail | B13: 2.3188139 | D13: Rail | E13: 0.25 | G13: Rail | H13: 5.4690979
A14: Road | B14: 2.6209385 | D14: Road | E14: 0.24137931 | G14: Road | H14: 5.5421154
A15: Sea | B15: 2.3152813 | D15: Sea | E15: 0.23529412 | G15: Sea | H15: 4.9702938
A16: Grand Total | B16: 2.277158 | D16: Grand Total | E16: 0.23 | G16: Grand Total | H16: 5.5481491
D19: Row Labels
A20: =SUM(supply_chain_data!M:M) -> 554.81491 | D20: Female
A21: =AVERAGE(supply_chain_data!U:U) -> 2.277158 | D21: Male
A22: =100*SUM(supply_chain_data!AB:AB)/COUNT(supply_chain_data!AB:AB) -> 23 | D22: Non-binary
A23: =AVERAGE(supply_chain_data!I:I) -> 15.96 | D23: Unknown
D24: Grand Total

Sheet Dashboard Tranportation Mode
